browserlog/SkeletonProvider.py
browserlog/__init__.py
browserlog/commands/InstallCommand.py
browserlog/config/__init__.py
browserlog/config/browserlog.py
browserlog/controllers/BrowserlogController.py
browserlog/providers/BrowserlogProvider.py
browserlog/providers/__init__.py
browserlog/templates/__init__.py
browserlog/templates/index.html
browserlog/utils/__init__.py
browserlog/utils/logs.py
browserlog/utils/packages.py
browserlog-1.0.0.dist-info/LICENSE.md
browserlog-1.0.0.dist-info/METADATA
browserlog-1.0.0.dist-info/WHEEL
browserlog-1.0.0.dist-info/top_level.txt
browserlog-1.0.0.dist-info/RECORD
